{"time":{"updated":"May 19, 2021 13:03:00 UTC","updatedISO":"2021-05-19T13:03:00+00:00","updateduk":"May 19, 2021 at 14:03 BST"},"disclaimer":"This data was produced from the CoinDesk Bitcoin Price Index (USD). Non-USD currency data converted using hourly conversion rate from openexchangerates.org","chartName":"Bitcoin","bpi":{"USD":{"code":"USD","symbol":"&#36;","rate":"33,078.5106","description":"United States Dollar","rate_float":33078.5106},"GBP":{"code":"GBP","symbol":"&pound;","rate":"23,368.2476","description":"British Pound Sterling","rate_float":23368.2476},"EUR":{"code":"EUR","symbol":"&euro;","rate":"27,098.2467","description":"Euro","rate_float":27098.2467},"CNY":{"code":"CNY","symbol":"&yen;","rate":"40,202.5000","description":"Chinese Yuan","rate_float":40202.5}}}